binmod/__init__.py
binmod/py.typed
binmod_runtime-0.1.3.dist-info/METADATA
binmod_runtime-0.1.3.dist-info/WHEEL
binmod_runtime-0.1.3.dist-info/licenses/LICENSE
binmod_runtime-0.1.3.dist-info/RECORD
