Metadata-Version: 2.4
Name: binmod-runtime
Version: 0.1.3
Summary: WASM based plugin runtime for Python
Project-URL: repository, https://gitlab.com/binmod/binmod-runtime-py
Author-email: Tim Pogue <me@pogue.dev>
License: MIT
License-File: LICENSE
Requires-Python: >=3.10
Requires-Dist: orjson>=3.10.18
Requires-Dist: pydantic>=2.11.4
Requires-Dist: wasmtime>=32.0.0
